edx_braze/__init__.py
edx_braze/apps.py
edx_braze/signals.py
edx_braze/settings/__init__.py
edx_braze/settings/common.py
edx_braze/settings/production.py
platform_plugin_braze-2.1.1.dist-info/LICENSE
platform_plugin_braze-2.1.1.dist-info/METADATA
platform_plugin_braze-2.1.1.dist-info/WHEEL
platform_plugin_braze-2.1.1.dist-info/entry_points.txt
platform_plugin_braze-2.1.1.dist-info/top_level.txt
platform_plugin_braze-2.1.1.dist-info/RECORD
