Metadata-Version: 2.1
Name: platform-plugin-braze
Version: 2.1.1
Summary: Custom Braze integration for edx.org's edx-platform deployment
Home-page: https://github.com/edx/platform-plugin-braze
Author: edX
Author-email: oscm@edx.org
Keywords: Python edx
Classifier: Development Status :: 5 - Production/Stable
Classifier: Framework :: Django
Classifier: Framework :: Django :: 3.2
Classifier: Framework :: Django :: 4.0
Classifier: Intended Audience :: Developers
Classifier: License :: Other/Proprietary License
Classifier: Natural Language :: English
Classifier: Programming Language :: Python :: 3
Classifier: Programming Language :: Python :: 3.8
Requires-Python: >=3.8
License-File: LICENSE
Requires-Dist: Django >=2.2
Requires-Dist: edx-django-utils
Requires-Dist: requests
